labeva/__init__.py
labeva/__version__.py
labeva/fit.py
labeva/func.py
labeva/math.py
labeva/plot.py
labeva-2.1.0.dist-info/LICENSE
labeva-2.1.0.dist-info/METADATA
labeva-2.1.0.dist-info/WHEEL
labeva-2.1.0.dist-info/RECORD
