Metadata-Version: 2.1
Name: labeva
Version: 2.1.0
Summary: ETs Laboratory Evaluation Suit
Home-page: https://github.com/et15/labeva
License: GPLv3+
Author: Erik Thiel
Author-email: erik.thiel@students.uni-mainz.de
Requires-Python: >=3.10,<3.13
Classifier: Development Status :: 3 - Alpha
Classifier: Intended Audience :: Science/Research
Classifier: License :: OSI Approved :: GNU General Public License v3 or later (GPLv3+)
Classifier: License :: Other/Proprietary License
Classifier: Programming Language :: Python :: 3
Classifier: Programming Language :: Python :: 3.10
Classifier: Programming Language :: Python :: 3.11
Classifier: Programming Language :: Python :: 3.12
Classifier: Programming Language :: Python :: 3.9
Classifier: Topic :: Scientific/Engineering :: Physics
Requires-Dist: lmfit (>=1.2.0)
Requires-Dist: matplotlib (>=3.7.1)
Requires-Dist: numpy (>=1.24.3)
Requires-Dist: scipy (>=1.10.1)
Project-URL: Documentation, https://labeva.docs.et15.eu/
Project-URL: Repository, https://github.com/et15/labeva
